paginators/__init__.py
paginators/apps.py
paginators/namepaginator.py
paginators/stringpaginator.py
paginators/templates/paginators/paginator.html
paginators/templatetags/__init__.py
paginators/templatetags/paginator.py
paginators-1.0.0.dist-info/licenses/LICENSE
paginators-1.0.0.dist-info/WHEEL
paginators-1.0.0.dist-info/METADATA
paginators-1.0.0.dist-info/RECORD
