Metadata-Version: 2.4
Name: paginators
Version: 1.0.0
Summary: Some missing paginators for Django
Author-email: kaleissin <kaleissin@gmail.com>
Requires-Python: >= 3.0
License-Expression: MIT
License-File: LICENSE
Requires-Dist: Django
Project-URL: Source, https://codeberg.org/Kaleissin/django-paginators
